[
    {
        "name": "id",
        "dbType": "integer,true",
        "htmlType": null,
        "validations": null,
        "searchable": false,
        "fillable": false,
        "primary": true,
        "inForm": false,
        "inIndex": false
    },
    {
        "name": "countries_name",
        "dbType": "string",
        "htmlType": "text",
        "validations": null,
        "searchable": true,
        "fillable": true,
        "primary": false,
        "inForm": true,
        "inIndex": true
    },
    {
        "name": "countries_iso_code_2",
        "dbType": "string",
        "htmlType": "text",
        "validations": null,
        "searchable": true,
        "fillable": true,
        "primary": false,
        "inForm": true,
        "inIndex": true
    },
    {
        "name": "countries_iso_code_3",
        "dbType": "string",
        "htmlType": "text",
        "validations": null,
        "searchable": true,
        "fillable": true,
        "primary": false,
        "inForm": true,
        "inIndex": true
    },
    {
        "name": "address_format_id",
        "dbType": "integer,false",
        "htmlType": null,
        "validations": null,
        "searchable": true,
        "fillable": true,
        "primary": false,
        "inForm": true,
        "inIndex": true
    },
    {
        "name": "active",
        "dbType": "integer,false",
        "htmlType": null,
        "validations": null,
        "searchable": true,
        "fillable": true,
        "primary": false,
        "inForm": true,
        "inIndex": true
    },
    {
        "name": "sort_order",
        "dbType": "integer,false",
        "htmlType": null,
        "validations": null,
        "searchable": true,
        "fillable": true,
        "primary": false,
        "inForm": true,
        "inIndex": true
    },
    {
        "name": "is_europe",
        "dbType": "integer,false",
        "htmlType": null,
        "validations": null,
        "searchable": true,
        "fillable": true,
        "primary": false,
        "inForm": true,
        "inIndex": true
    },
    {
        "name": "indiv_porto_active",
        "dbType": "integer,false",
        "htmlType": null,
        "validations": null,
        "searchable": true,
        "fillable": true,
        "primary": false,
        "inForm": true,
        "inIndex": true
    },
    {
        "name": "indiv_porto",
        "dbType": "float,7,2",
        "htmlType": null,
        "validations": null,
        "searchable": true,
        "fillable": true,
        "primary": false,
        "inForm": true,
        "inIndex": true
    },
    {
        "name": "indiv_porto_freigrenze",
        "dbType": "integer,false",
        "htmlType": null,
        "validations": null,
        "searchable": true,
        "fillable": true,
        "primary": false,
        "inForm": true,
        "inIndex": true
    },
    {
        "name": "created_at",
        "dbType": "datetime",
        "htmlType": "date",
        "validations": null,
        "searchable": false,
        "fillable": false,
        "primary": false,
        "inForm": false,
        "inIndex": false
    },
    {
        "name": "updated_at",
        "dbType": "datetime",
        "htmlType": "date",
        "validations": null,
        "searchable": false,
        "fillable": false,
        "primary": false,
        "inForm": false,
        "inIndex": false
    },
    {
        "type": "relation",
        "relation": "mtm,,role_has_permissions"
    }
]